rackio_material
