Metadata-Version: 2.1
Name: rackio-mkdocs-material
Version: 0.0.1
Summary: A Material Design theme for MkDocs to Rackio projects
Home-page: https://squidfunk.github.io/mkdocs-material/
Author: Carlos Rivero
Author-email: cdrr.rivero@gmail.com
License: MIT
Keywords: rackio,mkdocs,documentation,theme
Platform: UNKNOWN
Classifier: Development Status :: 5 - Production/Stable
Classifier: Environment :: Web Environment
Classifier: License :: OSI Approved :: MIT License
Classifier: Programming Language :: JavaScript
Classifier: Programming Language :: Python
Classifier: Topic :: Documentation
Classifier: Topic :: Software Development :: Documentation
Classifier: Topic :: Text Processing :: Markup :: HTML
Requires-Dist: mkautodoc (==0.1.0)
Requires-Dist: mkdocs (==1.2.2)
Requires-Dist: Pygments (==2.9.0)
Requires-Dist: markdown (==3.3..4)
Requires-Dist: pymdown-extensions (==8.2)
Requires-Dist: mkdocs-material-extensions (==1.0.1)
